{
  "0": {
    "coherence": 4,
    "relevance": 3,
    "coverage": 4,
    "justification": "The explanation is coherent and covers the main aspects of the cluster, focusing on high-quality products and user satisfaction. However, it could be more specific about the technology domain, which might limit its relevance. The key phrases are relevant but could benefit from a stronger connection to the technology context.",
    "strengths": [
      "Clear and concise explanation",
      "Focus on key aspects of the cluster"
    ],
    "weaknesses": [
      "Limited domain relevance",
      "Could benefit from more specific technology context"
    ]
  },
  "1": {
    "coherence": 4,
    "relevance": 3,
    "coverage": 4,
    "justification": "The explanation is coherent in its focus on the relationship between cat, dog, felid, and canine. It connects to the broader topic of domesticated carnivores. However, it could be more specific about how these terms relate to AI or machine learning concepts.",
    "strengths": [
      "Clear focus on related terms",
      "Logical grouping of terms"
    ],
    "weaknesses": [
      "Lack of explicit connection to AI/ML context",
      "Limited depth in explaining the clustering process"
    ]
  }
}